podcast_transcript_convert/__init__.py
podcast_transcript_convert/__main__.py
podcast_transcript_convert/constants.py
podcast_transcript_convert/convert.py
podcast_transcript_convert/database.py
podcast_transcript_convert/errors.py
podcast_transcript_convert/file_typing.py
podcast_transcript_convert/file_utils.py
podcast_transcript_convert/py.typed
podcast_transcript_convert/converters/__init__.py
podcast_transcript_convert/converters/any_to_simple.py
podcast_transcript_convert/converters/html_to_json.py
podcast_transcript_convert/converters/json_to_json.py
podcast_transcript_convert/converters/json_to_simple.py
podcast_transcript_convert/converters/srt_to_json.py
podcast_transcript_convert/converters/vtt_to_json.py
podcast_transcript_convert/converters/xml_to_json.py
podcast_transcript_convert-0.1.2.dist-info/METADATA
podcast_transcript_convert-0.1.2.dist-info/WHEEL
podcast_transcript_convert-0.1.2.dist-info/entry_points.txt
podcast_transcript_convert-0.1.2.dist-info/licenses/LICENSE.txt
podcast_transcript_convert-0.1.2.dist-info/RECORD
