Metadata-Version: 2.3
Name: podcast-transcript-convert
Version: 0.1.2
Summary: Convert podcast transcripts from HTML, SRT, WebVtt, Podlove etc into PodcastIndex JSON.
Project-URL: Homepage, https://github.com/hbmartin/podcast-transcript-convert
Author-email: Harold Martin <Harold.Martin@gmail.com>
License-File: LICENSE.txt
Keywords: convert,pci,podcast,podcastindex,podlove,srt,transcripts,vtt,webvtt
Classifier: Development Status :: 4 - Beta
Classifier: Environment :: Console
Classifier: Intended Audience :: End Users/Desktop
Classifier: Intended Audience :: Science/Research
Classifier: License :: OSI Approved :: Apache Software License
Classifier: Programming Language :: Python :: 3.11
Classifier: Programming Language :: Python :: 3.12
Classifier: Typing :: Typed
Requires-Python: >=3.11
Requires-Dist: beautifulsoup4
Requires-Dist: loguru
Requires-Dist: lxml
Requires-Dist: webvtt-py
Provides-Extra: lint
Requires-Dist: pyroma; extra == 'lint'
Requires-Dist: pytest; extra == 'lint'
Requires-Dist: pytype; extra == 'lint'
Requires-Dist: ruff; extra == 'lint'
